{
    "lastUpdated": "2021-10-10 13:55",
    "results": {
        "Alfred Health - Pfizer Community Clinic": {
            "total": 0,
            "earliest": null
        },
        "Austin - Olivia Newton John": {
            "total": 1502,
            "earliest": "10/10 12:50 PM"
        },
        "Austin - Repatriation (Pfizer)": {
            "total": 646,
            "earliest": "10/10 9:50 AM"
        },
        "Bairnsdale City Oval": {
            "total": 70,
            "earliest": "11/10 6:34 PM"
        },
        "Ballan Vaccination Clinic": {
            "total": 0,
            "earliest": null
        },
        "Ballarat Community Clinic- Pfizer": {
            "total": 192,
            "earliest": "11/10 9:50 AM"
        },
        "Beechworth Vaccination Hub": {
            "total": 77,
            "earliest": "15/10 10:15 AM"
        },
        "Box Hill Town Hall Pfizer": {
            "total": 6,
            "earliest": "10/10 8:50 AM"
        },
        "Bright Hub - North East VIC": {
            "total": 3,
            "earliest": "25/10 11:15 AM"
        },
        "Cabrini Elsternwick": {
            "total": 443,
            "earliest": "10/10 9:12 AM"
        },
        "Campbellfield Ford Complex Drive Thru-Pfizer": {
            "total": 53,
            "earliest": "10/10 9:30 AM"
        },
        "Campbellfield Ford Complex Walk Ins-Pfizer": {
            "total": 125,
            "earliest": "10/10 8:50 AM"
        },
        "Casterton Memorial Hospital": {
            "total": 0,
            "earliest": null
        },
        "Cohealth City Town Hall": {
            "total": 41,
            "earliest": "14/10 11:50 AM"
        },
        "Cohealth Glenroy College Pop-up Clinic": {
            "total": 0,
            "earliest": null
        },
        "Colac Area Health - COPACC": {
            "total": 12,
            "earliest": "14/10 10:40 AM"
        },
        "Convention Centre": {
            "total": 346,
            "earliest": "10/10 11:12 AM"
        },
        "Corryong health": {
            "total": 86,
            "earliest": "12/10 3:15 PM"
        },
        "Cranbourne Turf Club": {
            "total": 219,
            "earliest": "10/10 9:00 AM"
        },
        "DPV \u2013 Broadmeadows Town Hall": {
            "total": 44,
            "earliest": "10/10 10:30 AM"
        },
        "DPV Health Epping Secondary College": {
            "total": 0,
            "earliest": null
        },
        "DPV Health Fawkner": {
            "total": 0,
            "earliest": null
        },
        "DPV Health Oak Park Stadium": {
            "total": 0,
            "earliest": null
        },
        "Dandenong Hospital": {
            "total": 0,
            "earliest": null
        },
        "Dandenong Market Pop Up Vaccination Clinic": {
            "total": 0,
            "earliest": null
        },
        "EACH - Kilsyth": {
            "total": 313,
            "earliest": "14/10 11:40 AM"
        },
        "EACH \u2013 Pakenham, James Bathe Community and Sports Hub": {
            "total": 321,
            "earliest": "11/10 9:40 AM"
        },
        "East Grampians Health Services- Ararat": {
            "total": 94,
            "earliest": "19/10 1:40 PM"
        },
        "Eastern Health Mobile Clinic 1": {
            "total": 0,
            "earliest": null
        },
        "Eastland Vaccination Clinic Pfizer": {
            "total": 3,
            "earliest": "10/10 9:10 AM"
        },
        "Ford": {
            "total": 1,
            "earliest": "10/10 12:30 PM"
        },
        "Frankston Community Vaccination Hub - Bayside Centre": {
            "total": 254,
            "earliest": "10/10 9:30 AM"
        },
        "Gippsland Regional Sports Complex - Sale": {
            "total": 143,
            "earliest": "13/10 11:41 AM"
        },
        "Glen Eira Community In-reach Vaccination Service": {
            "total": 20,
            "earliest": "11/10 9:30 AM"
        },
        "Goods Shed Warragul Railway Station": {
            "total": 185,
            "earliest": "13/10 9:48 AM"
        },
        "Horsham": {
            "total": 34,
            "earliest": "12/10 9:50 AM"
        },
        "Hotel Quarantine \u2013 AHC": {
            "total": 0,
            "earliest": null
        },
        "IPC Health": {
            "total": 392,
            "earliest": "12/10 11:55 AM"
        },
        "KCLC - Kyabram Health Vaccination Clinic": {
            "total": 406,
            "earliest": "12/10 1:40 PM"
        },
        "Kilmore District Health Sub Hub": {
            "total": 1,
            "earliest": "11/10 12:40 PM"
        },
        "Kyneton - Central Highlands Rural Health": {
            "total": 50,
            "earliest": "12/10 3:45 PM"
        },
        "La Trobe University (Pfizer)": {
            "total": 3,
            "earliest": "10/10 9:00 AM"
        },
        "Leongatha Community Clinic": {
            "total": 173,
            "earliest": "11/10 1:00 PM"
        },
        "Mansfield Vaccination Clinic": {
            "total": 5,
            "earliest": "12/10 10:10 AM"
        },
        "McIntosh Centre - Shepparton Showgrounds - Pfizer": {
            "total": 2115,
            "earliest": "11/10 10:20 AM"
        },
        "Melbourne Showgrounds": {
            "total": 1228,
            "earliest": "10/10 8:15 AM"
        },
        "Melton Drive-Through Vaccination Centre": {
            "total": 269,
            "earliest": "10/10 8:50 AM"
        },
        "Melton Indoor Vaccination Centre - Woodgrove": {
            "total": 925,
            "earliest": "10/10 8:25 AM"
        },
        "Monash Community Outreach": {
            "total": 0,
            "earliest": null
        },
        "Monash Medical Centre": {
            "total": 0,
            "earliest": null
        },
        "Mt Beauty Vaccination Hub": {
            "total": 59,
            "earliest": "21/10 10:45 AM"
        },
        "Myrtleford Vaccination Hub": {
            "total": 53,
            "earliest": "22/10 10:45 AM"
        },
        "NCN Health": {
            "total": 305,
            "earliest": "12/10 12:02 PM"
        },
        "NCN Health Nathalia Pop Up": {
            "total": 0,
            "earliest": null
        },
        "NCN Health Numurkah Pop Up": {
            "total": 49,
            "earliest": "22/10 10:40 AM"
        },
        "NCN Health Yarrawonga Pop Up": {
            "total": 66,
            "earliest": "22/10 2:00 PM"
        },
        "NH - Plenty Ranges Arts & Convention Centre": {
            "total": 251,
            "earliest": "10/10 7:50 AM"
        },
        "Northeast Health Wangaratta": {
            "total": 270,
            "earliest": "11/10 4:21 PM"
        },
        "Orbost Regional Health": {
            "total": 0,
            "earliest": null
        },
        "Portland District Health": {
            "total": 0,
            "earliest": null
        },
        "RMH Pfizer": {
            "total": 0,
            "earliest": null
        },
        "Roxburgh College \u2013 Pop-up \u2013 DPV Health": {
            "total": 1,
            "earliest": "10/10 12:00 PM"
        },
        "Royal Exhibition Building - Pfizer": {
            "total": 395,
            "earliest": "10/10 8:40 AM"
        },
        "SWH - Camperdown": {
            "total": 126,
            "earliest": "12/10 10:10 AM"
        },
        "Sandown Racecourse": {
            "total": 380,
            "earliest": "10/10 9:00 AM"
        },
        "Sandown Racecourse Drive Through Vaccination Clinic": {
            "total": 65,
            "earliest": "10/10 9:00 AM"
        },
        "Sandringham Vaccination Centre": {
            "total": 1,
            "earliest": "28/10 11:10 AM"
        },
        "Seymour Health": {
            "total": 81,
            "earliest": "12/10 11:10 AM"
        },
        "St George Greek Orthodox Church Hall - Thornbury": {
            "total": 0,
            "earliest": null
        },
        "St John of God Berwick": {
            "total": 56,
            "earliest": "12/10 2:40 PM"
        },
        "St Vincent\u2019s Hospital Melbourne - Pfizer": {
            "total": 0,
            "earliest": null
        },
        "Star Health - CC - Betty Day Centre - Pfizer": {
            "total": 172,
            "earliest": "11/10 2:15 PM"
        },
        "Star Health - CC - Malvern Town Hall - Pfizer": {
            "total": 140,
            "earliest": "18/10 10:24 AM"
        },
        "Star Health - CC - Port Melbourne Town Hall - Pfizer": {
            "total": 340,
            "earliest": "11/10 11:20 AM"
        },
        "Star Health - Mass Vaccination Centre - Prahran Town Hall": {
            "total": 133,
            "earliest": "11/10 1:07 PM"
        },
        "Sunshine Hospital": {
            "total": 320,
            "earliest": "10/10 10:15 AM"
        },
        "Traralgon Racecourse": {
            "total": 100,
            "earliest": "14/10 10:52 AM"
        },
        "WDHS - Balmoral Clinic": {
            "total": 0,
            "earliest": null
        },
        "WDHS \u2013 Hamilton Base Hospital": {
            "total": 0,
            "earliest": null
        },
        "Warrnambool \u2013 SWH Vaccination Centre": {
            "total": 2,
            "earliest": "29/10 12:00 PM"
        },
        "Werribee - St Vincent's Private": {
            "total": 565,
            "earliest": "11/10 1:15 PM"
        },
        "Werribee Mercy": {
            "total": 0,
            "earliest": null
        },
        "Whitten Oval - Footscray": {
            "total": 0,
            "earliest": null
        },
        "Wodonga Vaccination Hub": {
            "total": 730,
            "earliest": "21/10 7:15 PM"
        },
        "Wonthaggi Town Hall": {
            "total": 685,
            "earliest": "12/10 10:12 AM"
        },
        "Wyndham Drive-Through Vaccination Centre": {
            "total": 278,
            "earliest": "10/10 9:30 AM"
        },
        "Wyndham Indoor Vaccination Centre \u2013 Eagle Stadium": {
            "total": 242,
            "earliest": "10/10 8:00 AM"
        },
        "Yarram Medical Centre": {
            "total": 0,
            "earliest": null
        },
        "Your Community Health Mobile Clinic": {
            "total": 0,
            "earliest": null
        }
    }
}