{
    "lastUpdated": "2021-10-04 07:30",
    "results": {
        "Alfred Health - Pfizer Community Clinic": {
            "total": 0,
            "earliest": null
        },
        "Austin - Olivia Newton John": {
            "total": 0,
            "earliest": null
        },
        "Austin - Repatriation (Pfizer)": {
            "total": 101,
            "earliest": "26/10 10:30 AM"
        },
        "Bairnsdale City Oval": {
            "total": 253,
            "earliest": "4/10 9:24 AM"
        },
        "Ballan Vaccination Clinic": {
            "total": 0,
            "earliest": null
        },
        "Ballarat Community Clinic- Pfizer": {
            "total": 1629,
            "earliest": "10/10 1:10 PM"
        },
        "Beechworth Vaccination Hub": {
            "total": 78,
            "earliest": "7/10 1:45 PM"
        },
        "Box Hill Town Hall Pfizer": {
            "total": 14,
            "earliest": "28/10 8:40 AM"
        },
        "Bright Hub - North East VIC": {
            "total": 7,
            "earliest": "18/10 9:30 AM"
        },
        "Cabrini Elsternwick": {
            "total": 0,
            "earliest": null
        },
        "Campbellfield Ford Complex Drive Thru-Pfizer": {
            "total": 130,
            "earliest": "18/10 10:00 AM"
        },
        "Campbellfield Ford Complex Walk Ins-Pfizer": {
            "total": 580,
            "earliest": "19/10 12:40 PM"
        },
        "Casterton Memorial Hospital": {
            "total": 0,
            "earliest": null
        },
        "Central Bayside Community health services": {
            "total": 0,
            "earliest": null
        },
        "Cohealth City Town Hall": {
            "total": 3,
            "earliest": "19/10 11:50 AM"
        },
        "Colac Area Health - COPACC": {
            "total": 64,
            "earliest": "19/10 11:20 AM"
        },
        "Convention Centre": {
            "total": 783,
            "earliest": "7/10 12:36 PM"
        },
        "Corryong health": {
            "total": 106,
            "earliest": "6/10 9:45 AM"
        },
        "Cranbourne Turf Club": {
            "total": 1333,
            "earliest": "10/10 10:20 AM"
        },
        "DPV \u2013 Broadmeadows Town Hall": {
            "total": 37,
            "earliest": "26/10 1:30 PM"
        },
        "DPV Health Fawkner": {
            "total": 0,
            "earliest": null
        },
        "Dandenong Hospital": {
            "total": 0,
            "earliest": null
        },
        "EACH - Kilsyth": {
            "total": 109,
            "earliest": "28/10 12:20 PM"
        },
        "EACH \u2013 Pakenham, James Bathe Community and Sports Hub": {
            "total": 41,
            "earliest": "6/10 10:50 AM"
        },
        "East Grampians Health Services- Ararat": {
            "total": 192,
            "earliest": "5/10 9:20 AM"
        },
        "Eastern Health Mobile Clinic 1": {
            "total": 0,
            "earliest": null
        },
        "Eastland Vaccination Clinic Pfizer": {
            "total": 1,
            "earliest": "29/10 9:20 AM"
        },
        "Ford": {
            "total": 1236,
            "earliest": "5/10 10:50 AM"
        },
        "Frankston Community Vaccination Hub - Bayside Centre": {
            "total": 977,
            "earliest": "5/10 12:40 PM"
        },
        "Gippsland Regional Sports Complex - Sale": {
            "total": 157,
            "earliest": "4/10 8:45 AM"
        },
        "Goods Shed Warragul Railway Station": {
            "total": 103,
            "earliest": "6/10 9:48 AM"
        },
        "Horsham": {
            "total": 329,
            "earliest": "5/10 10:10 AM"
        },
        "Hotel Quarantine \u2013 AHC": {
            "total": 0,
            "earliest": null
        },
        "IPC Health": {
            "total": 87,
            "earliest": "5/10 2:10 PM"
        },
        "KCLC - Kyabram Health Vaccination Clinic": {
            "total": 551,
            "earliest": "5/10 11:50 AM"
        },
        "Kilmore District Health Sub Hub": {
            "total": 0,
            "earliest": null
        },
        "Kyneton - Central Highlands Rural Health": {
            "total": 89,
            "earliest": "22/10 10:45 AM"
        },
        "Leongatha Community Clinic": {
            "total": 17,
            "earliest": "26/10 2:52 PM"
        },
        "Mansfield Vaccination Clinic": {
            "total": 113,
            "earliest": "5/10 9:10 AM"
        },
        "McIntosh Centre - Shepparton Showgrounds - Pfizer": {
            "total": 2526,
            "earliest": "5/10 12:20 PM"
        },
        "Melbourne Museum - Pfizer (REB relocated)": {
            "total": 945,
            "earliest": "12/10 10:20 AM"
        },
        "Melbourne Showgrounds": {
            "total": 1888,
            "earliest": "21/10 11:35 AM"
        },
        "Melton Drive-Through Vaccination Centre": {
            "total": 844,
            "earliest": "20/10 10:30 AM"
        },
        "Melton Indoor Vaccination Centre - Woodgrove": {
            "total": 2852,
            "earliest": "4/10 12:05 PM"
        },
        "Monash Community Outreach": {
            "total": 0,
            "earliest": null
        },
        "Monash Medical Centre": {
            "total": 0,
            "earliest": null
        },
        "Mt Beauty Vaccination Hub": {
            "total": 88,
            "earliest": "6/10 11:00 AM"
        },
        "Myrtleford Vaccination Hub": {
            "total": 85,
            "earliest": "8/10 11:45 AM"
        },
        "NCN Health": {
            "total": 321,
            "earliest": "12/10 10:34 AM"
        },
        "NCN Health Nathalia Pop Up": {
            "total": 4,
            "earliest": "29/10 10:40 AM"
        },
        "NCN Health Numurkah Pop Up": {
            "total": 49,
            "earliest": "15/10 11:12 AM"
        },
        "NCN Health Yarrawonga Pop Up": {
            "total": 70,
            "earliest": "10/10 10:18 AM"
        },
        "NH - Plenty Ranges Arts & Convention Centre": {
            "total": 485,
            "earliest": "3/11 2:20 PM"
        },
        "Northeast Health Wangaratta": {
            "total": 734,
            "earliest": "7/10 9:10 AM"
        },
        "Orbost Regional Health": {
            "total": 0,
            "earliest": null
        },
        "Portland District Health": {
            "total": 80,
            "earliest": "15/10 9:40 AM"
        },
        "RMH Pfizer": {
            "total": 0,
            "earliest": null
        },
        "SVHM ED - Pfizer": {
            "total": 0,
            "earliest": null
        },
        "SWH - Camperdown": {
            "total": 126,
            "earliest": "5/10 9:40 AM"
        },
        "Sandown Racecourse": {
            "total": 1910,
            "earliest": "10/10 1:50 PM"
        },
        "Sandown Racecourse Drive Through Vaccination Clinic": {
            "total": 54,
            "earliest": "1/11 9:20 AM"
        },
        "Sandringham Vaccination Centre": {
            "total": 2314,
            "earliest": "19/10 4:50 PM"
        },
        "Seymour Health": {
            "total": 65,
            "earliest": "5/10 11:15 AM"
        },
        "St George Greek Orthodox Church Hall - Thornbury": {
            "total": 0,
            "earliest": null
        },
        "St John of God Berwick": {
            "total": 13,
            "earliest": "28/10 3:50 PM"
        },
        "Star Health - CC - Betty Day Centre - Pfizer": {
            "total": 107,
            "earliest": "6/10 9:15 AM"
        },
        "Star Health - CC - Malvern Town Hall - Pfizer": {
            "total": 0,
            "earliest": null
        },
        "Star Health - CC - Port Melbourne Town Hall - Pfizer": {
            "total": 243,
            "earliest": "5/10 1:50 PM"
        },
        "Star Health - Mass Vaccination Centre - Prahran Town Hall": {
            "total": 0,
            "earliest": null
        },
        "Sunshine Hospital": {
            "total": 3372,
            "earliest": "4/10 12:55 PM"
        },
        "Traralgon Racecourse": {
            "total": 207,
            "earliest": "4/10 1:49 PM"
        },
        "WDHS - Balmoral Clinic": {
            "total": 0,
            "earliest": null
        },
        "WDHS \u2013 Hamilton Base Hospital": {
            "total": 318,
            "earliest": "5/10 1:50 PM"
        },
        "Warrnambool \u2013 SWH Vaccination Centre": {
            "total": 336,
            "earliest": "4/10 11:50 AM"
        },
        "Werribee - St Vincent's Private": {
            "total": 668,
            "earliest": "11/10 8:30 AM"
        },
        "Werribee Mercy": {
            "total": 0,
            "earliest": null
        },
        "Whitten Oval - Footscray": {
            "total": 0,
            "earliest": null
        },
        "Wodonga Vaccination Hub": {
            "total": 980,
            "earliest": "4/10 11:45 AM"
        },
        "Wonthaggi Town Hall": {
            "total": 223,
            "earliest": "4/10 12:40 PM"
        },
        "Wyndham Drive-Through Vaccination Centre": {
            "total": 351,
            "earliest": "27/10 9:10 AM"
        },
        "Wyndham Indoor Vaccination Centre \u2013 Eagle Stadium": {
            "total": 1825,
            "earliest": "5/10 12:25 PM"
        },
        "Yarram Medical Centre": {
            "total": 99,
            "earliest": "5/10 9:32 AM"
        },
        "Your Community Health Mobile Clinic": {
            "total": 0,
            "earliest": null
        }
    }
}