{
    "lastUpdated": "2021-10-05 08:07",
    "results": {
        "Alfred Health - Pfizer Community Clinic": {
            "total": 0,
            "earliest": null
        },
        "Austin - Olivia Newton John": {
            "total": 390,
            "earliest": "8/10 3:30 PM"
        },
        "Austin - Repatriation (Pfizer)": {
            "total": 489,
            "earliest": "6/10 2:00 PM"
        },
        "Bairnsdale City Oval": {
            "total": 339,
            "earliest": "5/10 10:04 AM"
        },
        "Ballan Vaccination Clinic": {
            "total": 0,
            "earliest": null
        },
        "Ballarat Community Clinic- Pfizer": {
            "total": 1331,
            "earliest": "8/10 8:50 AM"
        },
        "Beechworth Vaccination Hub": {
            "total": 89,
            "earliest": "8/10 2:45 PM"
        },
        "Box Hill Town Hall Pfizer": {
            "total": 2,
            "earliest": "28/10 12:00 PM"
        },
        "Bright Hub - North East VIC": {
            "total": 4,
            "earliest": "25/10 11:45 AM"
        },
        "Cabrini Elsternwick": {
            "total": 0,
            "earliest": null
        },
        "Campbellfield Ford Complex Drive Thru-Pfizer": {
            "total": 260,
            "earliest": "6/10 2:45 PM"
        },
        "Campbellfield Ford Complex Walk Ins-Pfizer": {
            "total": 497,
            "earliest": "26/10 2:20 PM"
        },
        "Casterton Memorial Hospital": {
            "total": 0,
            "earliest": null
        },
        "Central Bayside Community health services": {
            "total": 0,
            "earliest": null
        },
        "Cohealth City Town Hall": {
            "total": 1,
            "earliest": "5/10 3:00 PM"
        },
        "Colac Area Health - COPACC": {
            "total": 98,
            "earliest": "7/10 9:40 AM"
        },
        "Convention Centre": {
            "total": 465,
            "earliest": "6/10 9:24 AM"
        },
        "Corryong health": {
            "total": 113,
            "earliest": "12/10 1:15 PM"
        },
        "Cranbourne Turf Club": {
            "total": 1228,
            "earliest": "20/10 9:50 AM"
        },
        "DPV \u2013 Broadmeadows Town Hall": {
            "total": 41,
            "earliest": "25/10 11:15 AM"
        },
        "DPV Health Fawkner": {
            "total": 0,
            "earliest": null
        },
        "Dandenong Hospital": {
            "total": 0,
            "earliest": null
        },
        "EACH - Kilsyth": {
            "total": 30,
            "earliest": "4/11 1:20 PM"
        },
        "EACH \u2013 Pakenham, James Bathe Community and Sports Hub": {
            "total": 1,
            "earliest": "8/10 1:30 PM"
        },
        "East Grampians Health Services- Ararat": {
            "total": 228,
            "earliest": "5/10 11:20 AM"
        },
        "Eastern Health Mobile Clinic 1": {
            "total": 0,
            "earliest": null
        },
        "Eastland Vaccination Clinic Pfizer": {
            "total": 0,
            "earliest": null
        },
        "Ford": {
            "total": 1002,
            "earliest": "5/10 8:30 AM"
        },
        "Frankston Community Vaccination Hub - Bayside Centre": {
            "total": 806,
            "earliest": "16/10 12:50 PM"
        },
        "Gippsland Regional Sports Complex - Sale": {
            "total": 108,
            "earliest": "6/10 12:26 PM"
        },
        "Goods Shed Warragul Railway Station": {
            "total": 187,
            "earliest": "12/10 11:24 AM"
        },
        "Horsham": {
            "total": 378,
            "earliest": "5/10 11:50 AM"
        },
        "Hotel Quarantine \u2013 AHC": {
            "total": 0,
            "earliest": null
        },
        "IPC Health": {
            "total": 0,
            "earliest": null
        },
        "KCLC - Kyabram Health Vaccination Clinic": {
            "total": 520,
            "earliest": "5/10 11:30 AM"
        },
        "Kilmore District Health Sub Hub": {
            "total": 0,
            "earliest": null
        },
        "Kyneton - Central Highlands Rural Health": {
            "total": 73,
            "earliest": "12/10 12:00 PM"
        },
        "Leongatha Community Clinic": {
            "total": 190,
            "earliest": "5/10 9:45 AM"
        },
        "Mansfield Vaccination Clinic": {
            "total": 51,
            "earliest": "18/10 9:10 AM"
        },
        "McIntosh Centre - Shepparton Showgrounds - Pfizer": {
            "total": 2380,
            "earliest": "8/10 9:40 AM"
        },
        "Melbourne Museum - Pfizer (REB relocated)": {
            "total": 760,
            "earliest": "18/10 11:20 AM"
        },
        "Melbourne Showgrounds": {
            "total": 2120,
            "earliest": "18/10 10:15 AM"
        },
        "Melton Drive-Through Vaccination Centre": {
            "total": 1219,
            "earliest": "20/10 8:30 AM"
        },
        "Melton Indoor Vaccination Centre - Woodgrove": {
            "total": 2676,
            "earliest": "11/10 11:55 AM"
        },
        "Monash Community Outreach": {
            "total": 0,
            "earliest": null
        },
        "Monash Medical Centre": {
            "total": 0,
            "earliest": null
        },
        "Mt Beauty Vaccination Hub": {
            "total": 88,
            "earliest": "14/10 10:15 AM"
        },
        "Myrtleford Vaccination Hub": {
            "total": 82,
            "earliest": "8/10 2:45 PM"
        },
        "NCN Health": {
            "total": 382,
            "earliest": "18/10 11:54 AM"
        },
        "NCN Health Nathalia Pop Up": {
            "total": 8,
            "earliest": "8/10 3:04 PM"
        },
        "NCN Health Numurkah Pop Up": {
            "total": 47,
            "earliest": "22/10 10:00 AM"
        },
        "NCN Health Yarrawonga Pop Up": {
            "total": 77,
            "earliest": "15/10 1:28 PM"
        },
        "NH - Plenty Ranges Arts & Convention Centre": {
            "total": 695,
            "earliest": "31/10 12:50 PM"
        },
        "Northeast Health Wangaratta": {
            "total": 743,
            "earliest": "6/10 2:35 PM"
        },
        "Orbost Regional Health": {
            "total": 0,
            "earliest": null
        },
        "Portland District Health": {
            "total": 64,
            "earliest": "15/10 10:40 AM"
        },
        "RMH Pfizer": {
            "total": 0,
            "earliest": null
        },
        "SVHM ED - Pfizer": {
            "total": 0,
            "earliest": null
        },
        "SWH - Camperdown": {
            "total": 81,
            "earliest": "5/10 11:40 AM"
        },
        "Sandown Racecourse": {
            "total": 1679,
            "earliest": "28/10 11:10 AM"
        },
        "Sandown Racecourse Drive Through Vaccination Clinic": {
            "total": 90,
            "earliest": "8/11 9:50 AM"
        },
        "Sandringham Vaccination Centre": {
            "total": 2244,
            "earliest": "5/10 9:30 AM"
        },
        "Seymour Health": {
            "total": 0,
            "earliest": null
        },
        "St George Greek Orthodox Church Hall - Thornbury": {
            "total": 0,
            "earliest": null
        },
        "St John of God Berwick": {
            "total": 11,
            "earliest": "9/10 2:50 PM"
        },
        "Star Health - CC - Betty Day Centre - Pfizer": {
            "total": 0,
            "earliest": null
        },
        "Star Health - CC - Malvern Town Hall - Pfizer": {
            "total": 0,
            "earliest": null
        },
        "Star Health - CC - Port Melbourne Town Hall - Pfizer": {
            "total": 68,
            "earliest": "13/10 10:50 AM"
        },
        "Star Health - Mass Vaccination Centre - Prahran Town Hall": {
            "total": 0,
            "earliest": null
        },
        "Sunshine Hospital": {
            "total": 2903,
            "earliest": "13/10 12:25 PM"
        },
        "Traralgon Racecourse": {
            "total": 199,
            "earliest": "7/10 10:44 AM"
        },
        "WDHS - Balmoral Clinic": {
            "total": 0,
            "earliest": null
        },
        "WDHS \u2013 Hamilton Base Hospital": {
            "total": 306,
            "earliest": "6/10 11:10 AM"
        },
        "Warrnambool \u2013 SWH Vaccination Centre": {
            "total": 286,
            "earliest": "5/10 11:50 AM"
        },
        "Werribee - St Vincent's Private": {
            "total": 577,
            "earliest": "20/10 11:45 AM"
        },
        "Werribee Mercy": {
            "total": 0,
            "earliest": null
        },
        "Whitten Oval - Footscray": {
            "total": 0,
            "earliest": null
        },
        "Wodonga Vaccination Hub": {
            "total": 933,
            "earliest": "7/10 8:45 AM"
        },
        "Wonthaggi Town Hall": {
            "total": 42,
            "earliest": "5/10 12:20 PM"
        },
        "Wyndham Drive-Through Vaccination Centre": {
            "total": 512,
            "earliest": "27/10 9:30 AM"
        },
        "Wyndham Indoor Vaccination Centre \u2013 Eagle Stadium": {
            "total": 1812,
            "earliest": "13/10 12:55 PM"
        },
        "Yarram Medical Centre": {
            "total": 124,
            "earliest": "5/10 10:04 AM"
        },
        "Your Community Health Mobile Clinic": {
            "total": 0,
            "earliest": null
        }
    }
}